mcp_video_converter/__init__.py
mcp_video_converter/py.typed
mcp_video_converter/server.py
mcp_video_converter/tools.py
mseep_mcp_video_converter-0.1.1.dist-info/licenses/LICENSE
mseep_mcp_video_converter-0.1.1.dist-info/METADATA
mseep_mcp_video_converter-0.1.1.dist-info/WHEEL
mseep_mcp_video_converter-0.1.1.dist-info/entry_points.txt
mseep_mcp_video_converter-0.1.1.dist-info/top_level.txt
mseep_mcp_video_converter-0.1.1.dist-info/RECORD
